pyfb_direction/__init__.py
pyfb_direction/admin.py
pyfb_direction/api.py
pyfb_direction/apps.py
pyfb_direction/forms.py
pyfb_direction/models.py
pyfb_direction/resources.py
pyfb_direction/serializers.py
pyfb_direction/sql_config.py
pyfb_direction/urls.py
pyfb_direction/views.py
pyfb_direction/migrations/0001_initial.py
pyfb_direction/migrations/0002_auto_20190130_1804.py
pyfb_direction/migrations/0003_auto_20190327_1733.py
pyfb_direction/migrations/0004_auto_20200420_1605.py
pyfb_direction/migrations/__init__.py
pyfb_direction/static/css/pyfb_direction.css
pyfb_direction/static/js/pyfb_direction.js
pyfb_direction/templates/base.html
pyfb_direction/templates/pyfb_direction/carrier_detail.html
pyfb_direction/templates/pyfb_direction/carrier_form.html
pyfb_direction/templates/pyfb_direction/carrier_list.html
pyfb_direction/templates/pyfb_direction/country_detail.html
pyfb_direction/templates/pyfb_direction/country_form.html
pyfb_direction/templates/pyfb_direction/country_list.html
pyfb_direction/templates/pyfb_direction/destination_detail.html
pyfb_direction/templates/pyfb_direction/destination_form.html
pyfb_direction/templates/pyfb_direction/destination_list.html
pyfb_direction/templates/pyfb_direction/prefix_detail.html
pyfb_direction/templates/pyfb_direction/prefix_form.html
pyfb_direction/templates/pyfb_direction/prefix_list.html
pyfb_direction/templates/pyfb_direction/region_detail.html
pyfb_direction/templates/pyfb_direction/region_form.html
pyfb_direction/templates/pyfb_direction/region_list.html
pyfb_direction/templates/pyfb_direction/type_detail.html
pyfb_direction/templates/pyfb_direction/type_form.html
pyfb_direction/templates/pyfb_direction/type_list.html
pyfb_direction-1.0.4.dist-info/DESCRIPTION.rst
pyfb_direction-1.0.4.dist-info/METADATA
pyfb_direction-1.0.4.dist-info/RECORD
pyfb_direction-1.0.4.dist-info/WHEEL
pyfb_direction-1.0.4.dist-info/metadata.json
pyfb_direction-1.0.4.dist-info/top_level.txt
